physSpecPyCode/__init__.py
physSpecPyCode/physSpectrum.py
simplePhysSpectrum/__init__.py
simplePhysSpectrum/physSpectrum.py
simplePhysSpectrum-0.0.2.dist-info/LICENCE
simplePhysSpectrum-0.0.2.dist-info/METADATA
simplePhysSpectrum-0.0.2.dist-info/WHEEL
simplePhysSpectrum-0.0.2.dist-info/top_level.txt
simplePhysSpectrum-0.0.2.dist-info/RECORD
