Metadata-Version: 2.1
Name: simplePhysSpectrum
Version: 0.0.2
Summary: A small example package
Home-page: https://github.com/ChrisSWDavis/simplePhysSpectrum/
Author: Chris Davis
Author-email: ChrisSWDavis@gmail.com
License: MIT
Platform: UNKNOWN
Classifier: Programming Language :: Python :: 3
Classifier: License :: OSI Approved :: MIT License
Classifier: Operating System :: OS Independent
Requires-Dist: matplotlib (==3.5.2)
Requires-Dist: numpy (==1.22.4)
Requires-Dist: pandas (==1.4.2)
Requires-Dist: setuptools (==45.2.0)
Requires-Dist: tqdm (==4.64.0)
